odoo/addons/account_bank_statement_reopen_skip_undo_reconciliation/README.rst
odoo/addons/account_bank_statement_reopen_skip_undo_reconciliation/__init__.py
odoo/addons/account_bank_statement_reopen_skip_undo_reconciliation/__manifest__.py
odoo/addons/account_bank_statement_reopen_skip_undo_reconciliation/i18n/account_bank_statement_reopen_skip_undo_reconciliation.pot
odoo/addons/account_bank_statement_reopen_skip_undo_reconciliation/models/__init__.py
odoo/addons/account_bank_statement_reopen_skip_undo_reconciliation/models/account_bank_statement.py
odoo/addons/account_bank_statement_reopen_skip_undo_reconciliation/models/account_bank_statement_line.py
odoo/addons/account_bank_statement_reopen_skip_undo_reconciliation/models/account_move.py
odoo/addons/account_bank_statement_reopen_skip_undo_reconciliation/models/account_move_line.py
odoo/addons/account_bank_statement_reopen_skip_undo_reconciliation/readme/CONTRIBUTORS.rst
odoo/addons/account_bank_statement_reopen_skip_undo_reconciliation/readme/DESCRIPTION.rst
odoo/addons/account_bank_statement_reopen_skip_undo_reconciliation/static/description/icon.png
odoo/addons/account_bank_statement_reopen_skip_undo_reconciliation/static/description/index.html
odoo/addons/account_bank_statement_reopen_skip_undo_reconciliation/tests/__init__.py
odoo/addons/account_bank_statement_reopen_skip_undo_reconciliation/tests/test_account_bank_statement.py
odoo/addons/account_bank_statement_reopen_skip_undo_reconciliation/views/account_bank_statement_views.xml
odoo_addon_account_bank_statement_reopen_skip_undo_reconciliation-15.0.1.0.1.dist-info/METADATA
odoo_addon_account_bank_statement_reopen_skip_undo_reconciliation-15.0.1.0.1.dist-info/WHEEL
odoo_addon_account_bank_statement_reopen_skip_undo_reconciliation-15.0.1.0.1.dist-info/top_level.txt
odoo_addon_account_bank_statement_reopen_skip_undo_reconciliation-15.0.1.0.1.dist-info/RECORD
